tests/__init__.py
tests/test_telegram.py
tmwad/__init__.py
tmwad/telegram.py
tmwad-0.1.dist-info/LICENSE.txt
tmwad-0.1.dist-info/METADATA
tmwad-0.1.dist-info/WHEEL
tmwad-0.1.dist-info/top_level.txt
tmwad-0.1.dist-info/RECORD
