Metadata-Version: 2.1
Name: tmwad
Version: 0.1
Summary: A package for sending Telegram messages
Home-page: https://github.com/kalanakt/tmwad
Author: kalanakt
Author-email: e19198@eng.pdn.ac.lk
License-File: LICENSE.txt
Requires-Dist: requests
